{
  "$id": "product",
  "$schema": "https://schema.yext.com/config/schema/document-schema/v1",
  "primaryKey": "entityId",
  "type": "object",
  "description": "Use this entity type to store information about the products you sell.",
  "properties": {
    "accountId": {
      "$ref": "https://schema.yext.com/fields/yext/accountId"
    },
    "brand": {
      "$ref": "https://schema.yext.com/fields/yext/brand"
    },
    "color": {
      "$ref": "https://schema.yext.com/fields/yext/color"
    },
    "entityId": {
      "$ref": "https://schema.yext.com/fields/yext/entityId"
    },
    "externalEntityId": {
      "$ref": "https://schema.yext.com/fields/yext/externalEntityId"
    },
    "gtin": {
      "$ref": "https://schema.yext.com/fields/yext/gtin"
    },
    "keywords": {
      "$ref": "https://schema.yext.com/fields/yext/keywords"
    },
    "landingPageUrl": {
      "$ref": "https://schema.yext.com/fields/yext/landingPageUrl"
    },
    "locale": {
      "$ref": "https://schema.yext.com/fields/yext/locale"
    },
    "matchingSearchIds": {
      "$ref": "https://schema.yext.com/fields/yext/matchingSearchIds"
    },
    "name": {
      "$ref": "https://schema.yext.com/fields/yext/name"
    },
    "nudgeEnabled": {
      "$ref": "https://schema.yext.com/fields/yext/nudgeEnabled"
    },
    "parentProduct": {
      "$ref": "https://schema.yext.com/fields/yext/parentProduct"
    },
    "photoGallery": {
      "$ref": "https://schema.yext.com/fields/yext/photoGallery"
    },
    "price": {
      "$ref": "https://schema.yext.com/fields/yext/price"
    },
    "primaryConversationContact": {
      "$ref": "https://schema.yext.com/fields/yext/primaryConversationContact"
    },
    "richTextDescription": {
      "$ref": "https://schema.yext.com/fields/yext/richTextDescription"
    },
    "salesChannel": {
      "$ref": "https://schema.yext.com/fields/yext/salesChannel"
    },
    "size": {
      "$ref": "https://schema.yext.com/fields/yext/size"
    },
    "sku": {
      "$ref": "https://schema.yext.com/fields/yext/sku"
    },
    "stockStatus": {
      "$ref": "https://schema.yext.com/fields/yext/stockStatus"
    },
    "timezone": {
      "$ref": "https://schema.yext.com/fields/yext/timezone"
    },
    "videos": {
      "$ref": "https://schema.yext.com/fields/yext/videos"
    }
  },
  "required": [
    "entityId",
    "externalEntityId",
    "locale",
    "name"
  ],
  "title": "Product",
  "titlePlural": "Products",
  "yext.entity_type_id": 30000
}